{
  "id": "68fd6ffb-b0b6-4ef5-a796-9d8c894503a9",
  "prevId": "00000000-0000-0000-0000-000000000000",
  "version": "7",
  "dialect": "postgresql",
  "tables": {
    "public.companies": {
      "name": "companies",
      "schema": "",
      "columns": {
        "company_id": {
          "name": "company_id",
          "type": "integer",
          "primaryKey": true,
          "notNull": true,
          "identity": {
            "type": "always",
            "name": "companies_company_id_seq",
            "schema": "public",
            "increment": "1",
            "startWith": "1",
            "minValue": "1",
            "maxValue": "2147483647",
            "cache": "1",
            "cycle": false
          }
        },
        "company_name": {
          "name": "company_name",
          "type": "text",
          "primaryKey": false,
          "notNull": true
        },
        "industry": {
          "name": "industry",
          "type": "text",
          "primaryKey": false,
          "notNull": false
        }
      },
      "indexes": {},
      "foreignKeys": {},
      "compositePrimaryKeys": {},
      "uniqueConstraints": {},
      "policies": {},
      "checkConstraints": {},
      "isRLSEnabled": false
    },
    "public.drives": {
      "name": "drives",
      "schema": "",
      "columns": {
        "drive_id": {
          "name": "drive_id",
          "type": "integer",
          "primaryKey": true,
          "notNull": true,
          "identity": {
            "type": "always",
            "name": "drives_drive_id_seq",
            "schema": "public",
            "increment": "1",
            "startWith": "1",
            "minValue": "1",
            "maxValue": "2147483647",
            "cache": "1",
            "cycle": false
          }
        },
        "company_id": {
          "name": "company_id",
          "type": "integer",
          "primaryKey": false,
          "notNull": true
        },
        "drive_date": {
          "name": "drive_date",
          "type": "timestamp",
          "primaryKey": false,
          "notNull": false
        },
        "drive_type": {
          "name": "drive_type",
          "type": "drive_type",
          "typeSchema": "public",
          "primaryKey": false,
          "notNull": true
        },
        "min_package_lpa": {
          "name": "min_package_lpa",
          "type": "numeric",
          "primaryKey": false,
          "notNull": false
        },
        "max_package_lpa": {
          "name": "max_package_lpa",
          "type": "numeric",
          "primaryKey": false,
          "notNull": false
        }
      },
      "indexes": {},
      "foreignKeys": {
        "drives_company_id_companies_company_id_fk": {
          "name": "drives_company_id_companies_company_id_fk",
          "tableFrom": "drives",
          "tableTo": "companies",
          "columnsFrom": [
            "company_id"
          ],
          "columnsTo": [
            "company_id"
          ],
          "onDelete": "no action",
          "onUpdate": "no action"
        }
      },
      "compositePrimaryKeys": {},
      "uniqueConstraints": {},
      "policies": {},
      "checkConstraints": {},
      "isRLSEnabled": false
    },
    "public.officer_monthly_snapshot": {
      "name": "officer_monthly_snapshot",
      "schema": "",
      "columns": {
        "snapshot_id": {
          "name": "snapshot_id",
          "type": "integer",
          "primaryKey": true,
          "notNull": true,
          "identity": {
            "type": "always",
            "name": "officer_monthly_snapshot_snapshot_id_seq",
            "schema": "public",
            "increment": "1",
            "startWith": "1",
            "minValue": "1",
            "maxValue": "2147483647",
            "cache": "1",
            "cycle": false
          }
        },
        "officer_id": {
          "name": "officer_id",
          "type": "integer",
          "primaryKey": false,
          "notNull": true
        },
        "month": {
          "name": "month",
          "type": "integer",
          "primaryKey": false,
          "notNull": true
        },
        "year": {
          "name": "year",
          "type": "integer",
          "primaryKey": false,
          "notNull": true
        },
        "starting_pool": {
          "name": "starting_pool",
          "type": "integer",
          "primaryKey": false,
          "notNull": true
        },
        "target": {
          "name": "target",
          "type": "numeric",
          "primaryKey": false,
          "notNull": false
        }
      },
      "indexes": {},
      "foreignKeys": {
        "officer_monthly_snapshot_officer_id_placement_officers_officer_id_fk": {
          "name": "officer_monthly_snapshot_officer_id_placement_officers_officer_id_fk",
          "tableFrom": "officer_monthly_snapshot",
          "tableTo": "placement_officers",
          "columnsFrom": [
            "officer_id"
          ],
          "columnsTo": [
            "officer_id"
          ],
          "onDelete": "no action",
          "onUpdate": "no action"
        }
      },
      "compositePrimaryKeys": {},
      "uniqueConstraints": {},
      "policies": {},
      "checkConstraints": {},
      "isRLSEnabled": false
    },
    "public.placement_officers": {
      "name": "placement_officers",
      "schema": "",
      "columns": {
        "officer_id": {
          "name": "officer_id",
          "type": "integer",
          "primaryKey": true,
          "notNull": true,
          "identity": {
            "type": "always",
            "name": "placement_officers_officer_id_seq",
            "schema": "public",
            "increment": "1",
            "startWith": "1",
            "minValue": "1",
            "maxValue": "2147483647",
            "cache": "1",
            "cycle": false
          }
        },
        "user_id": {
          "name": "user_id",
          "type": "integer",
          "primaryKey": false,
          "notNull": true
        },
        "name": {
          "name": "name",
          "type": "text",
          "primaryKey": false,
          "notNull": true
        },
        "phone": {
          "name": "phone",
          "type": "text",
          "primaryKey": false,
          "notNull": false
        },
        "school_id": {
          "name": "school_id",
          "type": "integer",
          "primaryKey": false,
          "notNull": true
        }
      },
      "indexes": {},
      "foreignKeys": {
        "placement_officers_user_id_users_user_id_fk": {
          "name": "placement_officers_user_id_users_user_id_fk",
          "tableFrom": "placement_officers",
          "tableTo": "users",
          "columnsFrom": [
            "user_id"
          ],
          "columnsTo": [
            "user_id"
          ],
          "onDelete": "no action",
          "onUpdate": "no action"
        },
        "placement_officers_school_id_schools_school_id_fk": {
          "name": "placement_officers_school_id_schools_school_id_fk",
          "tableFrom": "placement_officers",
          "tableTo": "schools",
          "columnsFrom": [
            "school_id"
          ],
          "columnsTo": [
            "school_id"
          ],
          "onDelete": "no action",
          "onUpdate": "no action"
        }
      },
      "compositePrimaryKeys": {},
      "uniqueConstraints": {},
      "policies": {},
      "checkConstraints": {},
      "isRLSEnabled": false
    },
    "public.placements": {
      "name": "placements",
      "schema": "",
      "columns": {
        "placement_id": {
          "name": "placement_id",
          "type": "integer",
          "primaryKey": true,
          "notNull": true,
          "identity": {
            "type": "always",
            "name": "placements_placement_id_seq",
            "schema": "public",
            "increment": "1",
            "startWith": "1",
            "minValue": "1",
            "maxValue": "2147483647",
            "cache": "1",
            "cycle": false
          }
        },
        "student_id": {
          "name": "student_id",
          "type": "integer",
          "primaryKey": false,
          "notNull": true
        },
        "officer_id": {
          "name": "officer_id",
          "type": "integer",
          "primaryKey": false,
          "notNull": false
        },
        "drive_id": {
          "name": "drive_id",
          "type": "integer",
          "primaryKey": false,
          "notNull": false
        },
        "placement_type": {
          "name": "placement_type",
          "type": "placement_type",
          "typeSchema": "public",
          "primaryKey": false,
          "notNull": true
        },
        "package_lpa": {
          "name": "package_lpa",
          "type": "numeric",
          "primaryKey": false,
          "notNull": false
        },
        "offer_status": {
          "name": "offer_status",
          "type": "offer_status",
          "typeSchema": "public",
          "primaryKey": false,
          "notNull": true
        },
        "is_self_placed": {
          "name": "is_self_placed",
          "type": "boolean",
          "primaryKey": false,
          "notNull": true,
          "default": false
        },
        "placement_month": {
          "name": "placement_month",
          "type": "integer",
          "primaryKey": false,
          "notNull": true
        },
        "placement_year": {
          "name": "placement_year",
          "type": "integer",
          "primaryKey": false,
          "notNull": true
        }
      },
      "indexes": {},
      "foreignKeys": {
        "placements_student_id_students_student_id_fk": {
          "name": "placements_student_id_students_student_id_fk",
          "tableFrom": "placements",
          "tableTo": "students",
          "columnsFrom": [
            "student_id"
          ],
          "columnsTo": [
            "student_id"
          ],
          "onDelete": "no action",
          "onUpdate": "no action"
        },
        "placements_officer_id_placement_officers_officer_id_fk": {
          "name": "placements_officer_id_placement_officers_officer_id_fk",
          "tableFrom": "placements",
          "tableTo": "placement_officers",
          "columnsFrom": [
            "officer_id"
          ],
          "columnsTo": [
            "officer_id"
          ],
          "onDelete": "no action",
          "onUpdate": "no action"
        },
        "placements_drive_id_drives_drive_id_fk": {
          "name": "placements_drive_id_drives_drive_id_fk",
          "tableFrom": "placements",
          "tableTo": "drives",
          "columnsFrom": [
            "drive_id"
          ],
          "columnsTo": [
            "drive_id"
          ],
          "onDelete": "no action",
          "onUpdate": "no action"
        }
      },
      "compositePrimaryKeys": {},
      "uniqueConstraints": {},
      "policies": {},
      "checkConstraints": {},
      "isRLSEnabled": false
    },
    "public.program_officer_assignments": {
      "name": "program_officer_assignments",
      "schema": "",
      "columns": {
        "program_id": {
          "name": "program_id",
          "type": "integer",
          "primaryKey": false,
          "notNull": true
        },
        "officer_id": {
          "name": "officer_id",
          "type": "integer",
          "primaryKey": false,
          "notNull": true
        }
      },
      "indexes": {},
      "foreignKeys": {
        "program_officer_assignments_program_id_programs_program_id_fk": {
          "name": "program_officer_assignments_program_id_programs_program_id_fk",
          "tableFrom": "program_officer_assignments",
          "tableTo": "programs",
          "columnsFrom": [
            "program_id"
          ],
          "columnsTo": [
            "program_id"
          ],
          "onDelete": "no action",
          "onUpdate": "no action"
        },
        "program_officer_assignments_officer_id_placement_officers_officer_id_fk": {
          "name": "program_officer_assignments_officer_id_placement_officers_officer_id_fk",
          "tableFrom": "program_officer_assignments",
          "tableTo": "placement_officers",
          "columnsFrom": [
            "officer_id"
          ],
          "columnsTo": [
            "officer_id"
          ],
          "onDelete": "no action",
          "onUpdate": "no action"
        }
      },
      "compositePrimaryKeys": {
        "program_officer_assignments_program_id_officer_id_pk": {
          "name": "program_officer_assignments_program_id_officer_id_pk",
          "columns": [
            "program_id",
            "officer_id"
          ]
        }
      },
      "uniqueConstraints": {},
      "policies": {},
      "checkConstraints": {},
      "isRLSEnabled": false
    },
    "public.programs": {
      "name": "programs",
      "schema": "",
      "columns": {
        "program_id": {
          "name": "program_id",
          "type": "integer",
          "primaryKey": true,
          "notNull": true,
          "identity": {
            "type": "always",
            "name": "programs_program_id_seq",
            "schema": "public",
            "increment": "1",
            "startWith": "1",
            "minValue": "1",
            "maxValue": "2147483647",
            "cache": "1",
            "cycle": false
          }
        },
        "school_id": {
          "name": "school_id",
          "type": "integer",
          "primaryKey": false,
          "notNull": true
        },
        "program_name": {
          "name": "program_name",
          "type": "text",
          "primaryKey": false,
          "notNull": true
        },
        "credit_weightage": {
          "name": "credit_weightage",
          "type": "integer",
          "primaryKey": false,
          "notNull": true
        },
        "total_eligible_students": {
          "name": "total_eligible_students",
          "type": "integer",
          "primaryKey": false,
          "notNull": false
        }
      },
      "indexes": {},
      "foreignKeys": {
        "programs_school_id_schools_school_id_fk": {
          "name": "programs_school_id_schools_school_id_fk",
          "tableFrom": "programs",
          "tableTo": "schools",
          "columnsFrom": [
            "school_id"
          ],
          "columnsTo": [
            "school_id"
          ],
          "onDelete": "no action",
          "onUpdate": "no action"
        }
      },
      "compositePrimaryKeys": {},
      "uniqueConstraints": {},
      "policies": {},
      "checkConstraints": {},
      "isRLSEnabled": false
    },
    "public.schools": {
      "name": "schools",
      "schema": "",
      "columns": {
        "school_id": {
          "name": "school_id",
          "type": "integer",
          "primaryKey": true,
          "notNull": true,
          "identity": {
            "type": "always",
            "name": "schools_school_id_seq",
            "schema": "public",
            "increment": "1",
            "startWith": "1",
            "minValue": "1",
            "maxValue": "2147483647",
            "cache": "1",
            "cycle": false
          }
        },
        "school_name": {
          "name": "school_name",
          "type": "text",
          "primaryKey": false,
          "notNull": true
        }
      },
      "indexes": {},
      "foreignKeys": {},
      "compositePrimaryKeys": {},
      "uniqueConstraints": {},
      "policies": {},
      "checkConstraints": {},
      "isRLSEnabled": false
    },
    "public.students": {
      "name": "students",
      "schema": "",
      "columns": {
        "student_id": {
          "name": "student_id",
          "type": "integer",
          "primaryKey": true,
          "notNull": true,
          "identity": {
            "type": "always",
            "name": "students_student_id_seq",
            "schema": "public",
            "increment": "1",
            "startWith": "1",
            "minValue": "1",
            "maxValue": "2147483647",
            "cache": "1",
            "cycle": false
          }
        },
        "name": {
          "name": "name",
          "type": "text",
          "primaryKey": false,
          "notNull": true
        },
        "usn": {
          "name": "usn",
          "type": "text",
          "primaryKey": false,
          "notNull": true
        },
        "school_id": {
          "name": "school_id",
          "type": "integer",
          "primaryKey": false,
          "notNull": true
        },
        "program_id": {
          "name": "program_id",
          "type": "integer",
          "primaryKey": false,
          "notNull": true
        },
        "batch": {
          "name": "batch",
          "type": "integer",
          "primaryKey": false,
          "notNull": true
        },
        "is_active": {
          "name": "is_active",
          "type": "boolean",
          "primaryKey": false,
          "notNull": true,
          "default": true
        }
      },
      "indexes": {},
      "foreignKeys": {
        "students_school_id_schools_school_id_fk": {
          "name": "students_school_id_schools_school_id_fk",
          "tableFrom": "students",
          "tableTo": "schools",
          "columnsFrom": [
            "school_id"
          ],
          "columnsTo": [
            "school_id"
          ],
          "onDelete": "no action",
          "onUpdate": "no action"
        },
        "students_program_id_programs_program_id_fk": {
          "name": "students_program_id_programs_program_id_fk",
          "tableFrom": "students",
          "tableTo": "programs",
          "columnsFrom": [
            "program_id"
          ],
          "columnsTo": [
            "program_id"
          ],
          "onDelete": "no action",
          "onUpdate": "no action"
        }
      },
      "compositePrimaryKeys": {},
      "uniqueConstraints": {
        "students_usn_unique": {
          "name": "students_usn_unique",
          "nullsNotDistinct": false,
          "columns": [
            "usn"
          ]
        }
      },
      "policies": {},
      "checkConstraints": {},
      "isRLSEnabled": false
    },
    "public.users": {
      "name": "users",
      "schema": "",
      "columns": {
        "user_id": {
          "name": "user_id",
          "type": "integer",
          "primaryKey": true,
          "notNull": true,
          "identity": {
            "type": "always",
            "name": "users_user_id_seq",
            "schema": "public",
            "increment": "1",
            "startWith": "1",
            "minValue": "1",
            "maxValue": "2147483647",
            "cache": "1",
            "cycle": false
          }
        },
        "email": {
          "name": "email",
          "type": "text",
          "primaryKey": false,
          "notNull": true
        },
        "password_hash": {
          "name": "password_hash",
          "type": "text",
          "primaryKey": false,
          "notNull": true
        },
        "role": {
          "name": "role",
          "type": "role",
          "typeSchema": "public",
          "primaryKey": false,
          "notNull": true
        },
        "created_at": {
          "name": "created_at",
          "type": "timestamp",
          "primaryKey": false,
          "notNull": true,
          "default": "now()"
        }
      },
      "indexes": {},
      "foreignKeys": {},
      "compositePrimaryKeys": {},
      "uniqueConstraints": {
        "users_email_unique": {
          "name": "users_email_unique",
          "nullsNotDistinct": false,
          "columns": [
            "email"
          ]
        }
      },
      "policies": {},
      "checkConstraints": {},
      "isRLSEnabled": false
    }
  },
  "enums": {
    "public.drive_type": {
      "name": "drive_type",
      "schema": "public",
      "values": [
        "full_time",
        "internship",
        "capstone"
      ]
    },
    "public.offer_status": {
      "name": "offer_status",
      "schema": "public",
      "values": [
        "offered",
        "accepted",
        "rejected"
      ]
    },
    "public.placement_type": {
      "name": "placement_type",
      "schema": "public",
      "values": [
        "full_time",
        "internship",
        "capstone",
        "higher_studies"
      ]
    },
    "public.role": {
      "name": "role",
      "schema": "public",
      "values": [
        "admin",
        "officer",
        "viewer"
      ]
    }
  },
  "schemas": {},
  "sequences": {},
  "roles": {},
  "policies": {},
  "views": {},
  "_meta": {
    "columns": {},
    "schemas": {},
    "tables": {}
  }
}